ope/VERSION
ope/__init__.py
ope/cli.py
ope/parallel.py
ope/utils.py
ope/io/__init__.py
ope/io/base.py
ope/io/gff3.py
ope/io/hmmer.py
ope/io/infernal.py
ope/io/maf.py
ope/io/transdecoder.py
ope-0.8.dist-info/AUTHORS.rst
ope-0.8.dist-info/LICENSE
ope-0.8.dist-info/METADATA
ope-0.8.dist-info/WHEEL
ope-0.8.dist-info/entry_points.txt
ope-0.8.dist-info/top_level.txt
ope-0.8.dist-info/RECORD
