Metadata-Version: 2.1
Name: ope
Version: 0.8
Summary: Abstracts away running gnu-parallel on tools with FASTA input and provides parsers for some common formats produced by said tools.
Home-page: https://github.com/camillescott/ope
Author: Camille Scott
Author-email: cswel@ucdavis.edu
License: MIT license
Keywords: ope
Platform: UNKNOWN
Classifier: Development Status :: 2 - Pre-Alpha
Classifier: Intended Audience :: Developers
Classifier: License :: OSI Approved :: MIT License
Classifier: Natural Language :: English
Classifier: Programming Language :: Python :: 3
Classifier: Programming Language :: Python :: 3.6
Classifier: Programming Language :: Python :: 3.7
Classifier: Programming Language :: Python :: 3.8
Requires-Python: >=3.5
Requires-Dist: Click (>=7.0)
Requires-Dist: numpy
Requires-Dist: pandas
Requires-Dist: screed
